cipherdropx/__init__.py
cipherdropx/algorithm.py
cipherdropx/core.py
cipherdropx/executor.py
cipherdropx/h_parser.py
cipherdropx/l_parser.py
cipherdropx/l_regex.py
cipherdropx/parser.py
cipherdropx/regex.py
cipherdropx-1.0.1.dist-info/licenses/LICENSE
cipherdropx-1.0.1.dist-info/METADATA
cipherdropx-1.0.1.dist-info/WHEEL
cipherdropx-1.0.1.dist-info/top_level.txt
cipherdropx-1.0.1.dist-info/RECORD
